hashtags_extract.py
Hashtags_Extract-1.0.4.dist-info/LICENSE
Hashtags_Extract-1.0.4.dist-info/METADATA
Hashtags_Extract-1.0.4.dist-info/WHEEL
Hashtags_Extract-1.0.4.dist-info/top_level.txt
Hashtags_Extract-1.0.4.dist-info/RECORD
