Metadata-Version: 2.1
Name: Hashtags-Extract
Version: 1.0.4
Summary: Hashtags extract from string
Home-page: UNKNOWN
Author: Fayas Noushad
License: MIT
Project-URL: Tracker, https://github.com/FayasNoushad/Hashtags-Extract/issues
Project-URL: Source, https://github.com/FayasNoushad/Hashtags-Extract
Platform: UNKNOWN
Classifier: Intended Audience :: Developers
Classifier: Natural Language :: English
Classifier: Programming Language :: Python
Classifier: License :: OSI Approved :: MIT License
Classifier: Operating System :: OS Independent
Requires-Python: >=3.6
License-File: LICENSE
